lisntorch/__init__.py
lisntorch/evaluation.py
lisntorch/presets.py
lisntorch/viewdata.py
lisntorch-0.4.2.dist-info/METADATA
lisntorch-0.4.2.dist-info/WHEEL
lisntorch-0.4.2.dist-info/top_level.txt
lisntorch-0.4.2.dist-info/RECORD
