Metadata-Version: 2.4
Name: lisnTorch
Version: 0.4.2
Summary: 用于机器学习的辅助工具包
Author: lishuainan
Author-email: lishuainan0209@qq.com;lishuainan0209@163.com
Classifier: Programming Language :: Python :: 3
Classifier: License :: OSI Approved :: MIT License
Classifier: Operating System :: OS Independent
Requires-Python: >=3.6
Requires-Dist: matplotlib
Requires-Dist: numpy
Requires-Dist: torch
Requires-Dist: pandas
Requires-Dist: numpy
Requires-Dist: torchsummary
Requires-Dist: thop
Requires-Dist: pygame
Dynamic: author
Dynamic: author-email
Dynamic: classifier
Dynamic: description-content-type
Dynamic: requires-dist
Dynamic: requires-python
Dynamic: summary
